# Informative disassembler

## Small set-up:

```python
from idis import idis
from dis import dis

def foo():
    a = 1
    b = 2
    def f(x):
        global b
        b = 3
        y = x + 1
        return y 
    f(4)
    print(a)
```

---

## The difference between dis.dis and idis.idis:

### ***idis.idis*** ğŸ‘

```python
idis(foo) # tweakable via the 'columns' arg
```

    Disassembly of <code object foo at 0x00000184C62C3240, file "c:\Users\phant1e\Desktop\auto\test.py", line 56>:
        hasconst -> (None, 1, 2, <code object f at 0x00000184C61BFC90, file "c:\Users\phant1e\Desktop\auto\test.py", line 59>, 'foo.<locals>.f', 4)
        hasname -> ('print',)
        haslocal -> ('a', 'b', 'f')
    
                opname          opcode   flag       arg   pointsto         argval            argtype    hasarg
                Â¯Â¯Â¯Â¯Â¯Â¯          Â¯Â¯Â¯Â¯Â¯Â¯   Â¯Â¯Â¯Â¯       Â¯Â¯Â¯   Â¯Â¯Â¯Â¯Â¯Â¯Â¯Â¯         Â¯Â¯Â¯Â¯Â¯Â¯            Â¯Â¯Â¯Â¯Â¯Â¯Â¯    Â¯Â¯Â¯Â¯Â¯Â¯
    57        0 LOAD_CONST      100      hasconst     1   co_consts[1]     1                 int        âœ”
              2 STORE_FAST      125      haslocal     0   co_varnames[0]   a                 str        âœ”
    
    58        4 LOAD_CONST      100      hasconst     2   co_consts[2]     2                 int        âœ”
              6 STORE_FAST      125      haslocal     1   co_varnames[1]   b                 str        âœ”
    
    59        8 LOAD_CONST      100      hasconst     3   co_consts[3]     <code object f>   code       âœ”
             10 LOAD_CONST      100      hasconst     4   co_consts[4]     foo.<locals>.f    str        âœ”
             12 MAKE_FUNCTION   132                   0                                                 âœ”
             14 STORE_FAST      125      haslocal     2   co_varnames[2]   f                 str        âœ”
    
    64       16 LOAD_FAST       124      haslocal     2   co_varnames[2]   f                 str        âœ”
             18 LOAD_CONST      100      hasconst     5   co_consts[5]     4                 int        âœ”
             20 CALL_FUNCTION   131                   1                                                 âœ”
             22 POP_TOP         1                                                                         âœ–
    
    65       24 LOAD_GLOBAL     116      hasname      0   co_names[0]      print             str        âœ”
             26 LOAD_FAST       124      haslocal     0   co_varnames[0]   a                 str        âœ”
             28 CALL_FUNCTION   131                   1                                                 âœ”
             30 POP_TOP         1                                                                         âœ–
             32 LOAD_CONST      100      hasconst     0   co_consts[0]     None              NoneType   âœ”
             34 RETURN_VALUE    83                                                                        âœ–
    
    Disassembly of <code object f at 0x00000184C61BFC90, file "c:\Users\phant1e\Desktop\auto\test.py", line 59>:
        hasconst -> (None, 3, 1)
        hasname -> ('b',)
        haslocal -> ('x', 'y')
    
                opname          opcode   flag       arg   pointsto         argval            argtype    hasarg
                Â¯Â¯Â¯Â¯Â¯Â¯          Â¯Â¯Â¯Â¯Â¯Â¯   Â¯Â¯Â¯Â¯       Â¯Â¯Â¯   Â¯Â¯Â¯Â¯Â¯Â¯Â¯Â¯         Â¯Â¯Â¯Â¯Â¯Â¯            Â¯Â¯Â¯Â¯Â¯Â¯Â¯    Â¯Â¯Â¯Â¯Â¯Â¯
    61        0 LOAD_CONST      100      hasconst     1   co_consts[1]     3                 int        âœ”
              2 STORE_GLOBAL    97       hasname      0   co_names[0]      b                 str        âœ”
    
    62        4 LOAD_FAST       124      haslocal     0   co_varnames[0]   x                 str        âœ”
              6 LOAD_CONST      100      hasconst     2   co_consts[2]     1                 int        âœ”
              8 BINARY_ADD      23                                                                        âœ–
             10 STORE_FAST      125      haslocal     1   co_varnames[1]   y                 str        âœ”
    
    63       12 LOAD_FAST       124      haslocal     1   co_varnames[1]   y                 str        âœ”
             14 RETURN_VALUE    83                                                                        âœ–

### dis.dis ğŸ˜’

```python
dis(foo)
```
    
     57           0 LOAD_CONST               1 (1)
                  2 STORE_FAST               0 (a)
    
     58           4 LOAD_CONST               2 (2)
                  6 STORE_FAST               1 (b)
    
     59           8 LOAD_CONST               3 (<code object f at 0x000002C93C94FC90, file "c:\Users\phant1e\Desktop\auto\test.py", line 59>)
                 10 LOAD_CONST               4 ('foo.<locals>.f')
                 12 MAKE_FUNCTION            0
                 14 STORE_FAST               2 (f)
    
     64          16 LOAD_FAST                2 (f)
                 18 LOAD_CONST               5 (4)
                 20 CALL_FUNCTION            1
                 22 POP_TOP
    
     65          24 LOAD_GLOBAL              0 (print)
                 26 LOAD_FAST                0 (a)
                 28 CALL_FUNCTION            1
                 30 POP_TOP
                 32 LOAD_CONST               0 (None)
                 34 RETURN_VALUE
    
    Disassembly of <code object f at 0x000002C93C94FC90, file "c:\Users\phant1e\Desktop\auto\test.py", line 59>:
     61           0 LOAD_CONST               1 (3)
                  2 STORE_GLOBAL             0 (b)
    
     62           4 LOAD_FAST                0 (x)
                  6 LOAD_CONST               2 (1)
                  8 BINARY_ADD
                 10 STORE_FAST               1 (y)
    
     63          12 LOAD_FAST                1 (y)
                 14 RETURN_VALUE


Install:
    
    pip install git+https://github.com/phantie/informative-disassembler.git -U
